utn_fra/__init__.py
utn_fra/common_variables.py
utn_fra/datasets/__init__.py
utn_fra/datasets/utn_listas/__init__.py
utn_fra/datasets/utn_listas/autos/__init__.py
utn_fra/datasets/utn_listas/autos/matriz/__init__.py
utn_fra/datasets/utn_listas/autos/matriz/matriz_concesionaria.py
utn_fra/datasets/utn_listas/autos/simple/__init__.py
utn_fra/datasets/utn_listas/autos/simple/autos_cantidades.py
utn_fra/datasets/utn_listas/autos/simple/autos_ganancias.py
utn_fra/datasets/utn_listas/autos/simple/autos_marcas.py
utn_fra/datasets/utn_listas/autos/simple/autos_modelos.py
utn_fra/datasets/utn_listas/autos/simple/autos_precios.py
utn_fra/datasets/utn_listas/bzrp/__init__.py
utn_fra/datasets/utn_listas/bzrp/listas_duracion.py
utn_fra/datasets/utn_listas/bzrp/listas_nombres.py
utn_fra/datasets/utn_listas/bzrp/listas_vistas.py
utn_fra/datasets/utn_listas/bzrp/matriz_bzrp.py
utn_fra/datasets/utn_listas/heroes/__init__.py
utn_fra/datasets/utn_listas/heroes/complejo/__init__.py
utn_fra/datasets/utn_listas/heroes/complejo/lista_diccionario_heroes.py
utn_fra/datasets/utn_listas/heroes/complejo/listas_diccionario_heroes_hard.py
utn_fra/datasets/utn_listas/heroes/matriz/__init__.py
utn_fra/datasets/utn_listas/heroes/matriz/matriz_heroes.py
utn_fra/datasets/utn_listas/heroes/pp/__init__.py
utn_fra/datasets/utn_listas/heroes/pp/lista_alias.py
utn_fra/datasets/utn_listas/heroes/pp/lista_empresas.py
utn_fra/datasets/utn_listas/heroes/pp/lista_generos.py
utn_fra/datasets/utn_listas/heroes/pp/lista_inteligencias.py
utn_fra/datasets/utn_listas/heroes/pp/lista_nombres.py
utn_fra/datasets/utn_listas/heroes/pp/lista_poderes.py
utn_fra/datasets/utn_listas/heroes/pp/lista_razas.py
utn_fra/datasets/utn_listas/heroes/pp/lista_velocidades.py
utn_fra/datasets/utn_listas/heroes/simple/__init__.py
utn_fra/datasets/utn_listas/heroes/simple/lista_alturas.py
utn_fra/datasets/utn_listas/heroes/simple/lista_apodos.py
utn_fra/datasets/utn_listas/heroes/simple/lista_generos.py
utn_fra-1.0.1.11.dist-info/METADATA
utn_fra-1.0.1.11.dist-info/WHEEL
utn_fra-1.0.1.11.dist-info/entry_points.txt
utn_fra-1.0.1.11.dist-info/top_level.txt
utn_fra-1.0.1.11.dist-info/RECORD
