Metadata-Version: 2.4
Name: utn_fra
Version: 1.0.1.11
Summary: Set de datos con informacion para trabajos y examenes
Home-page: https://pypi.org/project/utn-fra/
Author: Facundo Falcone
Author-email: ffalcone@fra.utn.edu.ar
Maintainer: Facundo Falcone
Maintainer-email: ffalcone@fra.utn.edu.ar
Keywords: UTN_FRA,UTN-FRA,utn-fra,utn_fra
Classifier: Programming Language :: Python :: 3
Classifier: License :: OSI Approved :: MIT License
Classifier: Operating System :: OS Independent
Requires-Python: >=3.11
Requires-Dist: pillow
Requires-Dist: ffpyplayer
Requires-Dist: pymediainfo
Requires-Dist: tabulate
Requires-Dist: setuptools
Requires-Dist: pygame
Dynamic: author
Dynamic: author-email
Dynamic: classifier
Dynamic: description
Dynamic: description-content-type
Dynamic: home-page
Dynamic: keywords
Dynamic: maintainer
Dynamic: maintainer-email
Dynamic: requires-dist
Dynamic: requires-python
Dynamic: summary
